working_calendar/__init__.py
working_calendar/core.py
working_calendar/enumerations.py
working_calendar/exceptions.py
working_calendar-0.0.1.dist-info/METADATA
working_calendar-0.0.1.dist-info/RECORD
working_calendar-0.0.1.dist-info/WHEEL
working_calendar-0.0.1.dist-info/top_level.txt
