Metadata-Version: 2.1
Name: working-calendar
Version: 0.0.1
Summary: Utility for operate with working days.
Home-page: https://github.com/igorxut/working-calendar
Author: Igor Iakovlev
Author-email: igorxut@example.com
License: UNKNOWN
Platform: UNKNOWN
Classifier: Programming Language :: Python :: 3.6
Classifier: License :: OSI Approved :: MIT License
Classifier: Operating System :: OS Independent
Requires-Dist: typing
